aliyunsdkcore/__init__.py
aliyunsdkcore/client.py
python_sdkcore-1.0.3.dist-info/LICENSE
python_sdkcore-1.0.3.dist-info/METADATA
python_sdkcore-1.0.3.dist-info/WHEEL
python_sdkcore-1.0.3.dist-info/top_level.txt
python_sdkcore-1.0.3.dist-info/RECORD
